lunarcalendarx/__init__.py
lunarcalendarx/_calc.py
lunarcalendarx/_compact.py
lunarcalendarx/basefestival.py
lunarcalendarx/color.py
lunarcalendarx/command.py
lunarcalendarx/converter.py
lunarcalendarx/festival.py
lunarcalendarx/solarterm.py
lunarcalendarx-1.0.1.dist-info/licenses/LICENSE
lunarcalendarx-1.0.1.dist-info/METADATA
lunarcalendarx-1.0.1.dist-info/WHEEL
lunarcalendarx-1.0.1.dist-info/entry_points.txt
lunarcalendarx-1.0.1.dist-info/top_level.txt
lunarcalendarx-1.0.1.dist-info/RECORD
