Metadata-Version: 2.4
Name: LunarCalendarX
Version: 1.0.1
Summary: A lunar calendar converter, including a number of lunar and solar holidays, mainly from China.
Author-email: wolfhong <hongxucai1991@gmail.com>
Maintainer-email: chengchang <chengchangx@gmail.comm>
License: MIT License
Project-URL: Homepage, https://github.com/chengchang/LunarCalendarX
Project-URL: Issues, https://github.com/chengchang/LunarCalendarX/issues
Keywords: lunar calendar,festival,Chinese festivals,24 solar terms,solar calendar,lunar solar converter,lunisolar calendar
Classifier: License :: OSI Approved :: MIT License
Classifier: Programming Language :: Python :: 3.8
Classifier: Programming Language :: Python :: 3.9
Classifier: Programming Language :: Python :: 3.10
Classifier: Programming Language :: Python :: 3.11
Classifier: Programming Language :: Python :: 3.12
Classifier: Development Status :: 5 - Production/Stable
Classifier: Intended Audience :: Developers
Classifier: Topic :: Software Development :: Libraries
Classifier: Topic :: Utilities
Requires-Python: >=3.8
License-File: LICENSE
Requires-Dist: python-dateutil>=2.6.1
Requires-Dist: ephem>=3.7.5.3
Requires-Dist: pytz
Dynamic: license-file
